{"total":28,
	"rows":[
	{"clerk":"陳瑞克","startDate":"2016/12/1","endDate":"2999/12/31","inputDate":"2016/12/1  12:30:15 AM","inputPerson":"cio","lastEditDate":"2016/12/1  12:30:15 AM","lastEditMan":"cio"},
	{"clerk":"王大園","startDate":"2015/1/1","endDate":"2016/11/30","inputDate":"2015/1/1  10:24:31 AM","inputPerson":"cio","lastEditDate":"2016/12/1  12:30:15 AM","lastEditMan":"cio"},
	{"clerk":"陳瑞克","startDate":"2016/12/1","endDate":"2999/12/31","inputDate":"2016/12/1  12:30:15 AM","inputPerson":"cio","lastEditDate":"2016/12/1  12:30:15 AM","lastEditMan":"cio"},
	{"clerk":"王大園","startDate":"2015/1/1","endDate":"2016/11/30","inputDate":"2015/1/1  10:24:31 AM","inputPerson":"cio","lastEditDate":"2016/12/1  12:30:15 AM","lastEditMan":"cio"},
	{"clerk":"陳瑞克","startDate":"2016/12/1","endDate":"2999/12/31","inputDate":"2016/12/1  12:30:15 AM","inputPerson":"cio","lastEditDate":"2016/12/1  12:30:15 AM","lastEditMan":"cio"},
	{"clerk":"王大園","startDate":"2015/1/1","endDate":"2016/11/30","inputDate":"2015/1/1  10:24:31 AM","inputPerson":"cio","lastEditDate":"2016/12/1  12:30:15 AM","lastEditMan":"cio"},
	{"clerk":"陳瑞克","startDate":"2016/12/1","endDate":"2999/12/31","inputDate":"2016/12/1  12:30:15 AM","inputPerson":"cio","lastEditDate":"2016/12/1  12:30:15 AM","lastEditMan":"cio"},
	{"clerk":"王大園","startDate":"2015/1/1","endDate":"2016/11/30","inputDate":"2015/1/1  10:24:31 AM","inputPerson":"cio","lastEditDate":"2016/12/1  12:30:15 AM","lastEditMan":"cio"},
	{"clerk":"","startDate":"","endDate":"","inputDate":"","inputPerson":"","lastEditDate":"","lastEditMan":""},
	{"clerk":"","startDate":"","endDate":"","inputDate":"","inputPerson":"","lastEditDate":"","lastEditMan":""}
]}

